<?xml version="1.0" encoding="utf-8"?>
<!DOCTYPE hibernate-mapping PUBLIC "-//Hibernate/Hibernate Mapping DTD 3.0//EN"
"http://hibernate.sourceforge.net/hibernate-mapping-3.0.dtd">
<!-- 
    Mapping file autogenerated by MyEclipse Persistence Tools
-->
<hibernate-mapping>
    <class name="com.rskytech.pojo.MStep" table="M_STEP">
        <id name="MStepId" type="java.lang.String">
            <column name="M_STEP_ID" length="32" />
            <generator class="uuid.hex"></generator>
        </id>
        <many-to-one name="MMain" class="com.rskytech.pojo.MMain" fetch="select">
            <column name="MSI_ID" length="32" />
        </many-to-one>
        <property name="m11" type="java.lang.Integer">
            <column name="M11" precision="22" scale="0" />
        </property>
        <property name="m12" type="java.lang.Integer">
            <column name="M12" precision="22" scale="0" />
        </property>
        <property name="m13" type="java.lang.Integer">
            <column name="M13" precision="22" scale="0" />
        </property>
        <property name="m2" type="java.lang.Integer">
            <column name="M2" precision="22" scale="0" />
        </property>
        <property name="m3" type="java.lang.Integer">
            <column name="M3" precision="22" scale="0" />
        </property>
        <property name="m4" type="java.lang.Integer">
            <column name="M4" precision="22" scale="0" />
        </property>
        <property name="m5" type="java.lang.Integer">
            <column name="M5" precision="22" scale="0" />
        </property>
        <property name="createUser" type="java.lang.String">
            <column name="CREATE_USER" length="32" />
        </property>
        <property name="createDate" type="java.util.Date">
            <column name="CREATE_DATE" length="7" />
        </property>
        <property name="modifyUser" type="java.lang.String">
            <column name="MODIFY_USER" length="32" />
        </property>
        <property name="modifyDate" type="java.util.Date">
            <column name="MODIFY_DATE" length="7" />
        </property>
        <property name="mset" type="java.lang.Integer">
            <column name="MSET" precision="22" scale="0" />
        </property>
    </class>
</hibernate-mapping>
